monic/__init__.py
monic/py.typed
monic/version.py
monic/expressions/__init__.py
monic/expressions/context.py
monic/expressions/exceptions.py
monic/expressions/interpreter.py
monic/expressions/parser.py
monic/expressions/profiler.py
monic/expressions/registry.py
monic/expressions/security.py
monic/expressions/semantic.py
monic/runtime/__init__.py
monic/runtime/arrow.py
monic/runtime/datetime.py
monic/runtime/inspector.py
monic/runtime/json.py
monic/runtime/numpy.py
monic/runtime/pandas.py
monic/runtime/polars.py
monic/runtime/time.py
monic_framework-0.1.9.dist-info/LICENSE
monic_framework-0.1.9.dist-info/METADATA
monic_framework-0.1.9.dist-info/WHEEL
monic_framework-0.1.9.dist-info/top_level.txt
monic_framework-0.1.9.dist-info/RECORD
