Metadata-Version: 2.2
Name: monic-framework
Version: 0.1.9
Summary: Monic Framework
Author-email: "Cognica, Inc." <support@cognica.io>
License:                                  Apache License
Project-URL: Homepage, https://github.com/cognica-io/monic-framework
Project-URL: Repository, https://github.com/cognica-io/monic-framework
Project-URL: Issues, https://github.com/cognica-io/monic-framework/issues
Classifier: Development Status :: 5 - Production/Stable
Classifier: Intended Audience :: Developers
Classifier: License :: OSI Approved :: Apache Software License
Classifier: Programming Language :: Python :: 3 :: Only
Classifier: Programming Language :: Python :: 3.10
Classifier: Programming Language :: Python :: 3.11
Classifier: Programming Language :: Python :: 3.12
Classifier: Programming Language :: Python :: 3.13
Classifier: Topic :: Software Development :: Interpreters
Classifier: Topic :: Software Development :: Libraries :: Python Modules
Classifier: Typing :: Typed
Requires-Python: >=3.10
License-File: LICENSE
Provides-Extra: extra
Requires-Dist: pyarrow; extra == "extra"
Requires-Dist: numpy; extra == "extra"
Requires-Dist: pandas; extra == "extra"
Requires-Dist: polars; extra == "extra"
Provides-Extra: dev
Requires-Dist: coverage; extra == "dev"
Requires-Dist: pytest; extra == "dev"
Requires-Dist: pytest-cov; extra == "dev"
